polar_flow/__init__.py
polar_flow/auth.py
polar_flow/cli.py
polar_flow/client.py
polar_flow/exceptions.py
polar_flow/py.typed
polar_flow/endpoints/__init__.py
polar_flow/endpoints/activity.py
polar_flow/endpoints/activity_samples.py
polar_flow/endpoints/biosensing.py
polar_flow/endpoints/cardio_load.py
polar_flow/endpoints/continuous_hr.py
polar_flow/endpoints/exercises.py
polar_flow/endpoints/physical_info.py
polar_flow/endpoints/recharge.py
polar_flow/endpoints/sleep.py
polar_flow/endpoints/sleepwise.py
polar_flow/endpoints/users.py
polar_flow/models/__init__.py
polar_flow/models/activity.py
polar_flow/models/activity_samples.py
polar_flow/models/biosensing.py
polar_flow/models/cardio_load.py
polar_flow/models/continuous_hr.py
polar_flow/models/exercise.py
polar_flow/models/physical_info.py
polar_flow/models/recharge.py
polar_flow/models/sleep.py
polar_flow/models/sleepwise_alertness.py
polar_flow/models/sleepwise_bedtime.py
polar_flow/models/user.py
polar_flow_api-1.4.0.dist-info/METADATA
polar_flow_api-1.4.0.dist-info/WHEEL
polar_flow_api-1.4.0.dist-info/entry_points.txt
polar_flow_api-1.4.0.dist-info/licenses/LICENSE
polar_flow_api-1.4.0.dist-info/RECORD
