Metadata-Version: 2.4
Name: polar-flow-api
Version: 1.4.0
Summary: Modern async Python client for Polar AccessLink API
Project-URL: Homepage, https://github.com/StuMason/polar-flow
Project-URL: Documentation, https://github.com/StuMason/polar-flow
Project-URL: Repository, https://github.com/StuMason/polar-flow
Project-URL: Issues, https://github.com/StuMason/polar-flow/issues
Author-email: Stuart Mason <stu@stumason.dev>
License: MIT
License-File: LICENSE
Keywords: accesslink,api,exercise,fitness,health,hrv,polar,sleep
Classifier: Development Status :: 4 - Beta
Classifier: Framework :: Pydantic :: 2
Classifier: Intended Audience :: Developers
Classifier: License :: OSI Approved :: MIT License
Classifier: Programming Language :: Python :: 3
Classifier: Programming Language :: Python :: 3.11
Classifier: Programming Language :: Python :: 3.12
Classifier: Programming Language :: Python :: 3.13
Classifier: Topic :: Internet :: WWW/HTTP
Classifier: Topic :: Software Development :: Libraries :: Python Modules
Classifier: Typing :: Typed
Requires-Python: >=3.11
Requires-Dist: httpx>=0.27
Requires-Dist: pydantic>=2.0
Requires-Dist: rich>=13.0
Requires-Dist: typer>=0.12
Provides-Extra: dev
Requires-Dist: mypy>=1.10; extra == 'dev'
Requires-Dist: pytest-asyncio>=0.23; extra == 'dev'
Requires-Dist: pytest-cov>=5.0; extra == 'dev'
Requires-Dist: pytest-httpx>=0.30; extra == 'dev'
Requires-Dist: pytest>=8.0; extra == 'dev'
Requires-Dist: python-dotenv>=1.0; extra == 'dev'
Requires-Dist: ruff>=0.4; extra == 'dev'
Provides-Extra: docs
Requires-Dist: mkdocs-material>=9.5; extra == 'docs'
Requires-Dist: mkdocs>=1.5; extra == 'docs'
Requires-Dist: mkdocstrings[python]>=0.24; extra == 'docs'
